README.rst
setup.cfg
setup.py
EncryptHashPassword.egg-info/PKG-INFO
EncryptHashPassword.egg-info/SOURCES.txt
EncryptHashPassword.egg-info/dependency_links.txt
EncryptHashPassword.egg-info/entry_points.txt
EncryptHashPassword.egg-info/top_level.txt
genpassword/__init__.py
genpassword/genpassword.py