Metadata-Version: 1.1
Name: EncryptHashPassword
Version: 1.0.1
Summary: Use your domain, password and extra salt to encrypt password
Home-page: UNKNOWN
Author: BoscoTsang
Author-email: boscotsang3@gmail.com
License: MIT
Platform: UNKNOWN
Classifier: Development Status :: 3 - Alpha
Classifier: Environment :: Console
Classifier: Intended Audience :: Customer Service
Classifier: License :: OSI Approved :: MIT License
Classifier: Programming Language :: Python
Classifier: Topic :: Utilities
